dnac_device_list/__init__.py
dnac_device_list/device_list.py
dnac_device_list-1.2.dist-info/LICENSE
dnac_device_list-1.2.dist-info/METADATA
dnac_device_list-1.2.dist-info/WHEEL
dnac_device_list-1.2.dist-info/top_level.txt
dnac_device_list-1.2.dist-info/RECORD
