Metadata-Version: 2.1
Name: dnac-device-list
Version: 1.2
Summary: Get complete Device list inventory with location details from DNAC.
Author-email: Alexios Nersessian <nersessian@gmail.com>
Project-URL: Homepage, https://github.com/alekos3/DNAC_Device_Location
Classifier: Programming Language :: Python :: 3
Classifier: License :: OSI Approved :: MIT License
Classifier: Operating System :: OS Independent
Requires-Python: >=3.7
License-File: LICENSE
Requires-Dist: requests[security] (>=2.28)
